animeSexAnalyzer/__init__.py
animeSexAnalyzer/animeSexAnalyzer.py
anime_character_sex_analyzer-1.0.3.dist-info/METADATA
anime_character_sex_analyzer-1.0.3.dist-info/WHEEL
anime_character_sex_analyzer-1.0.3.dist-info/licenses/LICENSE
anime_character_sex_analyzer-1.0.3.dist-info/RECORD
