Metadata-Version: 2.3
Name: anime-character-sex-analyzer
Version: 1.0.3
Summary: Determines the sex of a character
Project-URL: Homepage, https://git.fearvel.de/tools/python/anime-character-sex-analyzer
Author-email: Andreas Schreiner <fearvel@proton.me>
License-File: LICENSE
Classifier: License :: OSI Approved :: MIT License
Requires-Dist: dghs-imgutils
